[
  {
    "title": "01/04 04:27 發布低溫特報",
    "oid": "2.16.886.101.20003.20008.20004",
    "sourcelink": "https://www.cwa.gov.tw/V8/C/P/Warning/W28.html?T=202501040427",
    "starttime": "20250104042700",
    "endtime": "20250704042700",
    "createdate": "20250104042700",
    "modifydate": "20250104060538"
  },
  {
    "title": "01/04 03:35 發布陸上強風特報",
    "oid": "2.16.886.101.20003.20008.20004",
    "sourcelink": "https://www.cwa.gov.tw/V8/C/P/Warning/W25.html?T=202501040335",
    "starttime": "20250104033500",
    "endtime": "20250704033500",
    "createdate": "20250104033500",
    "modifydate": "20250104060538"
  },
  {
    "title": "勞動部提出3面向6項策進作為健全就安基金管理",
    "oid": "2.16.886.101.20003.20063",
    "sourcelink": "http://www.mol.gov.tw/1607/1632/1633/77742/",
    "starttime": "20250104005753",
    "endtime": "20250704005753",
    "createdate": "20250104005753",
    "modifydate": "20250103180501"
  }
]
