[
  {
    "title": "12/19 05:30 發布陸上強風特報",
    "oid": "2.16.886.101.20003.20008.20004",
    "sourcelink": "https://www.cwa.gov.tw/V8/C/P/Warning/W25.html?T=202412190530",
    "starttime": "20241219053000",
    "endtime": "20250619053000",
    "createdate": "20241219053000",
    "modifydate": "20241219060556"
  },
  {
    "title": "12/19 04:25 發布低溫特報",
    "oid": "2.16.886.101.20003.20008.20004",
    "sourcelink": "https://www.cwa.gov.tw/V8/C/P/Warning/W28.html?T=202412190425",
    "starttime": "20241219042500",
    "endtime": "20250619042500",
    "createdate": "20241219042500",
    "modifydate": "20241219060556"
  }
]
