[
  {
    "title": "行使剩餘財產差額分配請求權取得之土地，得申請不課徵土地增值稅",
    "oid": "2.16.886.101.90028.20002.20070",
    "sourcelink": "https://www.tntb.gov.tw/news_view.php?qinfoid=10829&amp;lmenuid=5&amp;smenuid=109&amp;qtype=1",
    "starttime": "20251013T080101",
    "endtime": "20260413T080101",
    "createdate": "20251013T080101",
    "modifydate": "20251013T000609"
  },
  {
    "title": "財神好運到！阿華生活飲茶隆田店開出統一發票特別獎1000萬元",
    "oid": "2.16.886.101.20003.20004.20047",
    "sourcelink": "https://www.ntbsa.gov.tw/singlehtml/5e0e49a811b74b50b5a6486d38374285?cntId=2005b3aba3af41e493f06dad3211aa4c",
    "starttime": "20251013T000000",
    "endtime": "20260413T000000",
    "createdate": "20251013T000000",
    "modifydate": "20251013T060529"
  }
]
