[
  {
    "title": "01/12 04:29 發布低溫特報",
    "oid": "2.16.886.101.20003.20008.20081",
    "sourcelink": "https://www.cwa.gov.tw/V8/C/P/Warning/W28.html?T=202601120429",
    "starttime": "20260112T042900",
    "endtime": "20260712T042900",
    "createdate": "20260112T042900",
    "modifydate": "20260112T060600"
  },
  {
    "title": "115年度契稅查核啟動 財稅局提醒把握60日申報期限",
    "oid": "2.16.886.101.90028.20002.20070",
    "sourcelink": "https://www.tntb.gov.tw/news_view.php?qinfoid=10971&amp;lmenuid=5&amp;smenuid=109&amp;qtype=1",
    "starttime": "20260112T080101",
    "endtime": "20260712T080101",
    "createdate": "20260112T080101",
    "modifydate": "20260112T001331"
  },
  {
    "title": "114年度各類所得憑單(含信託)申報期間自115年1月1日起至2月2日止，請依限申報!",
    "oid": "2.16.886.101.20003.20004.20047",
    "sourcelink": "https://www.ntbsa.gov.tw/singlehtml/5e0e49a811b74b50b5a6486d38374285?cntId=05772a3d26af4694abe1079a10bc120c",
    "starttime": "20260112T000000",
    "endtime": "20260712T000000",
    "createdate": "20260112T000000",
    "modifydate": "20260112T060559"
  },
  {
    "title": "01/12 04:27 發布陸上強風特報",
    "oid": "2.16.886.101.20003.20008.20081",
    "sourcelink": "https://www.cwa.gov.tw/V8/C/P/Warning/W25.html?T=202601120427",
    "starttime": "20260112T042700",
    "endtime": "20260712T042700",
    "createdate": "20260112T042700",
    "modifydate": "20260112T060600"
  }
]
