[
  {
    "title": "09/21 03:00 發布長浪即時訊息",
    "oid": "2.16.886.101.20003.20008.20081",
    "sourcelink": "https://www.cwa.gov.tw/V8/C/P/Warning/W37.html?T=202509210300",
    "starttime": "20250921T030000",
    "endtime": "20260321T030000",
    "createdate": "20250921T030000",
    "modifydate": "20250921T060524"
  },
  {
    "title": "09/21 04:35 發布陸上強風特報",
    "oid": "2.16.886.101.20003.20008.20081",
    "sourcelink": "https://www.cwa.gov.tw/V8/C/P/Warning/W25.html?T=202509210435",
    "starttime": "20250921T043500",
    "endtime": "20260321T043500",
    "createdate": "20250921T043500",
    "modifydate": "20250921T060524"
  }
]
