[
  {
    "title": "申請電子繳納證明，環保又便利!",
    "oid": "2.16.886.101.90029.20002.20003.20004",
    "sourcelink": "",
    "starttime": "20250311090300",
    "endtime": "20250911090300",
    "createdate": "20250311090344",
    "modifydate": "20250311090500"
  },
  {
    "title": "稅捐處結合社會教育館「草地野餐音樂會」活動，邀您捐發票、換好禮",
    "oid": "2.16.886.101.90029.20002.20003.20004",
    "sourcelink": "",
    "starttime": "20250311092000",
    "endtime": "20250315092000",
    "createdate": "20250311092008",
    "modifydate": "20250311092200"
  },
  {
    "title": "北市圖3/30留學講座　探索法語世界：比利時留學趣",
    "oid": "2.16.886.101.90003.20002",
    "sourcelink": "https://www.gov.taipei/News_Content.aspx?n=F0DDAF49B89E9413&s=43CAD5D797A6452F",
    "starttime": "20250311000000",
    "endtime": "20250911000000",
    "createdate": "20250311000000",
    "modifydate": "20250311060840"
  },
  {
    "title": "03/11 05:30 發布濃霧特報",
    "oid": "2.16.886.101.20003.20008.20081",
    "sourcelink": "https://www.cwa.gov.tw/V8/C/P/Warning/W27.html?T=202503110530",
    "starttime": "20250311053000",
    "endtime": "20250911053000",
    "createdate": "20250311053000",
    "modifydate": "20250311060837"
  },
  {
    "title": "閒置住宅出租房屋稅享優惠稅率，最低只要1.5%",
    "oid": "2.16.886.101.90029.20002.20003.20004",
    "sourcelink": "",
    "starttime": "20250311093000",
    "endtime": "20250911093000",
    "createdate": "20250311093002",
    "modifydate": "20250311093500"
  },
  {
    "title": "稅捐處3月19日結合新甲國小「113學年校慶園遊會」辦理租稅宣導活動",
    "oid": "2.16.886.101.90029.20002.20003.20004",
    "sourcelink": "",
    "starttime": "20250311095900",
    "endtime": "20250911095900",
    "createdate": "20250311095937",
    "modifydate": "20250311100200"
  }
]
